hpm/__init__.py
hpm/cli.py
hpm/config.py
hpm/services/__init__.py
hpm/services/inspire_hep/__init__.py
hpm/services/inspire_hep/client.py
hpm/services/inspire_hep/objects.py
hpm/services/notion/__init__.py
hpm/services/notion/client.py
hpm/services/notion/objects/__init__.py
hpm/services/notion/objects/database.py
hpm/services/notion/objects/database_properties.py
hpm/services/notion/objects/page.py
hpm/services/notion/objects/page_properties.py
hpm/templates/paper.yml
hpm/utils.py
hep_paper_manager-0.4.0.dist-info/LICENSE
hep_paper_manager-0.4.0.dist-info/METADATA
hep_paper_manager-0.4.0.dist-info/WHEEL
hep_paper_manager-0.4.0.dist-info/entry_points.txt
hep_paper_manager-0.4.0.dist-info/RECORD
