Metadata-Version: 2.1
Name: hep-paper-manager
Version: 0.4.0
Summary: A command-line app helps add High Energy Physics (HEP) papers to a Notion database.
Home-page: https://github.com/Star9daisy/hep-paper-manager
License: MIT
Keywords: high-energy-physics,inspire-hep,notion,cli
Author: Star9daisy
Author-email: star9daisy@outlook.com
Requires-Python: >=3.11,<4.0
Classifier: License :: OSI Approved :: MIT License
Classifier: Programming Language :: Python :: 3
Classifier: Programming Language :: Python :: 3.11
Classifier: Programming Language :: Python :: 3.12
Classifier: Programming Language :: Python :: 3.13
Requires-Dist: eval-type-backport (>=0.2.0,<0.3.0)
Requires-Dist: pydantic (>=2.9.2,<3.0.0)
Requires-Dist: pyfiglet (>=1.0.2,<2.0.0)
Requires-Dist: pyyaml (>=6.0.2,<7.0.0)
Requires-Dist: requests (>=2.31.0,<3.0.0)
Requires-Dist: rich (>=13.4.1,<14.0.0)
Requires-Dist: tinydb (>=4.8.2,<5.0.0)
Requires-Dist: typeguard (>=4.4.1,<5.0.0)
Requires-Dist: typer (>=0.12.0,<0.13.0)
Requires-Dist: typing-extensions (>=4.6.3,<5.0.0)
Project-URL: Repository, https://github.com/Star9daisy/hep-paper-manager
